nx_config_swarfield/__init__.py
nx_config_swarfield/cli.py
nx_config_swarfield/config.py
nx_config_swarfield/exceptions.py
nx_config_swarfield/fill.py
nx_config_swarfield/format.py
nx_config_swarfield/path_resolution.py
nx_config_swarfield/secret_string.py
nx_config_swarfield/section.py
nx_config_swarfield/url.py
nx_config_swarfield/validation.py
nx_config_swarfield/_core/__init__.py
nx_config_swarfield/_core/config_meta.py
nx_config_swarfield/_core/entry_to_text.py
nx_config_swarfield/_core/fill_with_oracles.py
nx_config_swarfield/_core/generate_template.py
nx_config_swarfield/_core/iteration_utils.py
nx_config_swarfield/_core/naming_utils.py
nx_config_swarfield/_core/path_with_oracles.py
nx_config_swarfield/_core/section_entry.py
nx_config_swarfield/_core/section_meta.py
nx_config_swarfield/_core/type_checks.py
nx_config_swarfield/_core/typing_utils.py
nx_config_swarfield/_core/unset.py
nx_config_swarfield/_core/validator.py
nx_config_swarfield/test_utils/__init__.py
nx_config_swarfield/test_utils/updates.py
nx_config_swarfield-1.1.dist-info/LICENSE
nx_config_swarfield-1.1.dist-info/METADATA
nx_config_swarfield-1.1.dist-info/WHEEL
nx_config_swarfield-1.1.dist-info/top_level.txt
nx_config_swarfield-1.1.dist-info/RECORD
