Metadata-Version: 2.1
Name: nx_config_swarfield
Version: 1.1
Summary: A convenient way to configure python applications that makes it easy and natural to follow best practices and solves a variety of common issues encountered when using e.g. the 'configparser' library.
Author: Samuel Warfield
Author-email: swarfield@cloudflare.com
Project-URL: Bug Tracker, https://github.com/NextKraftwerke/PyConfig/issues
Project-URL: Documentation, https://nextkraftwerke.github.io/PyConfig/
Project-URL: Source Code, https://github.com/Warfields/PyConfig
Keywords: configuration,settings,yaml,toml,ini,env
Classifier: Development Status :: 4 - Beta
Classifier: Intended Audience :: Developers
Classifier: License :: OSI Approved :: GNU General Public License v3 (GPLv3)
Classifier: Operating System :: OS Independent
Classifier: Programming Language :: Python
Classifier: Programming Language :: Python :: 3
Classifier: Programming Language :: Python :: 3 :: Only
Classifier: Programming Language :: Python :: 3.6
Classifier: Programming Language :: Python :: 3.7
Classifier: Programming Language :: Python :: 3.8
Classifier: Programming Language :: Python :: 3.9
Classifier: Programming Language :: Python :: 3.10
Classifier: Programming Language :: Python :: 3.11
Classifier: Programming Language :: Python :: 3.12
Classifier: Topic :: Software Development
Requires-Python: <3.12,>=3.6
License-File: LICENSE
Requires-Dist: python-dateutil <3,>=2.8.2
Requires-Dist: pyyaml <7,>=6.0
Provides-Extra: coverage
Requires-Dist: coverage <7,>=6.0.2 ; extra == 'coverage'
Provides-Extra: docs
Requires-Dist: sphinx <5,>=4.2.0 ; extra == 'docs'
Requires-Dist: python-docs-theme <2022,>=2021.11.1 ; extra == 'docs'
Provides-Extra: format
Requires-Dist: black <23,>=22.3.0 ; extra == 'format'
Provides-Extra: tests
Provides-Extra: tox
Requires-Dist: tox <4,>=3.24.4 ; extra == 'tox'
